<?xml version="1.0" encoding="UTF-8" standalone="yes"?><imgdir name="01103000.img"><imgdir name="info"><int name="cash" value="1"/><canvas name="icon" width="35" height="35"><vector name="origin" x="0" y="32"/></canvas><canvas name="iconRaw" width="35" height="35"><vector name="origin" x="0" y="32"/></canvas><string name="islot" value="Sr"/><int name="reqDEX" value="0"/><int name="reqINT" value="0"/><int name="reqJob" value="0"/><int name="reqLevel" value="0"/><int name="reqLUK" value="0"/><int name="reqSTR" value="0"/><string name="vslot" value="Sr"/></imgdir><imgdir name="walk1"><imgdir name="0"><int name="delay" value="120"/><canvas name="cape" width="196" height="57"><vector name="origin" x="85" y="90"/><string name="z" value="tamingMobRear"/><vector name="lt" x="-55" y="-72"/><vector name="rb" x="48" y="-11"/><imgdir name="map"><vector name="navel" x="0" y="-46"/></imgdir></canvas></imgdir><imgdir name="1"><int name="delay" value="120"/><canvas name="cape" width="194" height="55"><vector name="origin" x="85" y="98"/><string name="z" value="tamingMobRear"/><vector name="lt" x="-55" y="-72"/><vector name="rb" x="48" y="-11"/><imgdir name="map"><vector name="navel" x="0" y="-45"/></imgdir></canvas></imgdir><imgdir name="2"><int name="delay" value="120"/><canvas name="cape" width="210" height="54"><vector name="origin" x="94" y="96"/><string name="z" value="tamingMobRear"/><vector name="lt" x="-55" y="-72"/><vector name="rb" x="48" y="-11"/><imgdir name="map"><vector name="navel" x="0" y="-44"/></imgdir></canvas></imgdir><imgdir name="3"><int name="delay" value="120"/><canvas name="cape" width="202" height="56"><vector name="origin" x="93" y="59"/><string name="z" value="tamingMobRear"/><vector name="lt" x="-55" y="-72"/><vector name="rb" x="48" y="-11"/><imgdir name="map"><vector name="navel" x="0" y="-46"/></imgdir></canvas></imgdir><imgdir name="4"><int name="delay" value="120"/><canvas name="cape" width="174" height="72"><vector name="origin" x="84" y="62"/><string name="z" value="tamingMobRear"/><vector name="lt" x="-55" y="-72"/><vector name="rb" x="48" y="-11"/><imgdir name="map"><vector name="navel" x="0" y="-47"/></imgdir></canvas></imgdir><imgdir name="5"><int name="delay" value="120"/><canvas name="cape" width="146" height="81"><vector name="origin" x="69" y="74"/><string name="z" value="tamingMobRear"/><vector name="lt" x="-55" y="-72"/><vector name="rb" x="48" y="-11"/><imgdir name="map"><vector name="navel" x="0" y="-48"/></imgdir></canvas></imgdir></imgdir><imgdir name="walk2"><imgdir name="0"><int name="delay" value="120"/><canvas name="cape" width="196" height="57"><vector name="origin" x="85" y="90"/><string name="z" value="tamingMobRear"/><vector name="lt" x="-55" y="-72"/><vector name="rb" x="48" y="-11"/><imgdir name="map"><vector name="navel" x="0" y="-46"/></imgdir></canvas></imgdir><imgdir name="1"><int name="delay" value="120"/><canvas name="cape" width="194" height="55"><vector name="origin" x="85" y="98"/><string name="z" value="tamingMobRear"/><vector name="lt" x="-55" y="-72"/><vector name="rb" x="48" y="-11"/><imgdir name="map"><vector name="navel" x="0" y="-45"/></imgdir></canvas></imgdir><imgdir name="2"><int name="delay" value="120"/><canvas name="cape" width="210" height="54"><vector name="origin" x="94" y="96"/><string name="z" value="tamingMobRear"/><vector name="lt" x="-55" y="-72"/><vector name="rb" x="48" y="-11"/><imgdir name="map"><vector name="navel" x="0" y="-44"/></imgdir></canvas></imgdir><imgdir name="3"><int name="delay" value="120"/><canvas name="cape" width="202" height="56"><vector name="origin" x="93" y="59"/><string name="z" value="tamingMobRear"/><vector name="lt" x="-55" y="-72"/><vector name="rb" x="48" y="-11"/><imgdir name="map"><vector name="navel" x="0" y="-46"/></imgdir></canvas></imgdir><imgdir name="4"><int name="delay" value="120"/><canvas name="cape" width="174" height="72"><vector name="origin" x="84" y="62"/><string name="z" value="tamingMobRear"/><vector name="lt" x="-55" y="-72"/><vector name="rb" x="48" y="-11"/><imgdir name="map"><vector name="navel" x="0" y="-47"/></imgdir></canvas></imgdir><imgdir name="5"><int name="delay" value="120"/><canvas name="cape" width="146" height="81"><vector name="origin" x="69" y="74"/><string name="z" value="tamingMobRear"/><vector name="lt" x="-55" y="-72"/><vector name="rb" x="48" y="-11"/><imgdir name="map"><vector name="navel" x="0" y="-48"/></imgdir></canvas></imgdir></imgdir><imgdir name="stand1"><imgdir name="0"><int name="delay" value="120"/><canvas name="cape" width="196" height="57"><vector name="origin" x="85" y="90"/><string name="z" value="tamingMobRear"/><vector name="lt" x="-55" y="-72"/><vector name="rb" x="48" y="-11"/><imgdir name="map"><vector name="navel" x="0" y="-46"/></imgdir></canvas></imgdir><imgdir name="1"><int name="delay" value="120"/><canvas name="cape" width="194" height="55"><vector name="origin" x="85" y="98"/><string name="z" value="tamingMobRear"/><vector name="lt" x="-55" y="-72"/><vector name="rb" x="48" y="-11"/><imgdir name="map"><vector name="navel" x="0" y="-45"/></imgdir></canvas></imgdir><imgdir name="2"><int name="delay" value="120"/><canvas name="cape" width="210" height="54"><vector name="origin" x="94" y="96"/><string name="z" value="tamingMobRear"/><vector name="lt" x="-55" y="-72"/><vector name="rb" x="48" y="-11"/><imgdir name="map"><vector name="navel" x="0" y="-44"/></imgdir></canvas></imgdir><imgdir name="3"><int name="delay" value="120"/><canvas name="cape" width="202" height="56"><vector name="origin" x="93" y="59"/><string name="z" value="tamingMobRear"/><vector name="lt" x="-55" y="-72"/><vector name="rb" x="48" y="-11"/><imgdir name="map"><vector name="navel" x="0" y="-46"/></imgdir></canvas></imgdir><imgdir name="4"><int name="delay" value="120"/><canvas name="cape" width="174" height="72"><vector name="origin" x="84" y="62"/><string name="z" value="tamingMobRear"/><vector name="lt" x="-55" y="-72"/><vector name="rb" x="48" y="-11"/><imgdir name="map"><vector name="navel" x="0" y="-47"/></imgdir></canvas></imgdir><imgdir name="5"><int name="delay" value="120"/><canvas name="cape" width="146" height="81"><vector name="origin" x="69" y="74"/><string name="z" value="tamingMobRear"/><vector name="lt" x="-55" y="-72"/><vector name="rb" x="48" y="-11"/><imgdir name="map"><vector name="navel" x="0" y="-48"/></imgdir></canvas></imgdir></imgdir><imgdir name="stand2"><imgdir name="0"><int name="delay" value="120"/><canvas name="cape" width="196" height="57"><vector name="origin" x="85" y="90"/><string name="z" value="tamingMobRear"/><vector name="lt" x="-55" y="-72"/><vector name="rb" x="48" y="-11"/><imgdir name="map"><vector name="navel" x="0" y="-46"/></imgdir></canvas></imgdir><imgdir name="1"><int name="delay" value="120"/><canvas name="cape" width="194" height="55"><vector name="origin" x="85" y="98"/><string name="z" value="tamingMobRear"/><vector name="lt" x="-55" y="-72"/><vector name="rb" x="48" y="-11"/><imgdir name="map"><vector name="navel" x="0" y="-45"/></imgdir></canvas></imgdir><imgdir name="2"><int name="delay" value="120"/><canvas name="cape" width="210" height="54"><vector name="origin" x="94" y="96"/><string name="z" value="tamingMobRear"/><vector name="lt" x="-55" y="-72"/><vector name="rb" x="48" y="-11"/><imgdir name="map"><vector name="navel" x="0" y="-44"/></imgdir></canvas></imgdir><imgdir name="3"><int name="delay" value="120"/><canvas name="cape" width="202" height="56"><vector name="origin" x="93" y="59"/><string name="z" value="tamingMobRear"/><vector name="lt" x="-55" y="-72"/><vector name="rb" x="48" y="-11"/><imgdir name="map"><vector name="navel" x="0" y="-46"/></imgdir></canvas></imgdir><imgdir name="4"><int name="delay" value="120"/><canvas name="cape" width="174" height="72"><vector name="origin" x="84" y="62"/><string name="z" value="tamingMobRear"/><vector name="lt" x="-55" y="-72"/><vector name="rb" x="48" y="-11"/><imgdir name="map"><vector name="navel" x="0" y="-47"/></imgdir></canvas></imgdir><imgdir name="5"><int name="delay" value="120"/><canvas name="cape" width="146" height="81"><vector name="origin" x="69" y="74"/><string name="z" value="tamingMobRear"/><vector name="lt" x="-55" y="-72"/><vector name="rb" x="48" y="-11"/><imgdir name="map"><vector name="navel" x="0" y="-48"/></imgdir></canvas></imgdir></imgdir><imgdir name="tired"><imgdir name="0"><int name="delay" value="120"/><canvas name="cape" width="196" height="57"><vector name="origin" x="85" y="90"/><string name="z" value="tamingMobRear"/><vector name="lt" x="-55" y="-72"/><vector name="rb" x="48" y="-11"/><imgdir name="map"><vector name="navel" x="0" y="-46"/></imgdir></canvas></imgdir><imgdir name="1"><int name="delay" value="120"/><canvas name="cape" width="194" height="55"><vector name="origin" x="85" y="98"/><string name="z" value="tamingMobRear"/><vector name="lt" x="-55" y="-72"/><vector name="rb" x="48" y="-11"/><imgdir name="map"><vector name="navel" x="0" y="-45"/></imgdir></canvas></imgdir><imgdir name="2"><int name="delay" value="120"/><canvas name="cape" width="210" height="54"><vector name="origin" x="94" y="96"/><string name="z" value="tamingMobRear"/><vector name="lt" x="-55" y="-72"/><vector name="rb" x="48" y="-11"/><imgdir name="map"><vector name="navel" x="0" y="-44"/></imgdir></canvas></imgdir><imgdir name="3"><int name="delay" value="120"/><canvas name="cape" width="202" height="56"><vector name="origin" x="93" y="59"/><string name="z" value="tamingMobRear"/><vector name="lt" x="-55" y="-72"/><vector name="rb" x="48" y="-11"/><imgdir name="map"><vector name="navel" x="0" y="-46"/></imgdir></canvas></imgdir><imgdir name="4"><int name="delay" value="120"/><canvas name="cape" width="174" height="72"><vector name="origin" x="84" y="62"/><string name="z" value="tamingMobRear"/><vector name="lt" x="-55" y="-72"/><vector name="rb" x="48" y="-11"/><imgdir name="map"><vector name="navel" x="0" y="-47"/></imgdir></canvas></imgdir><imgdir name="5"><int name="delay" value="120"/><canvas name="cape" width="146" height="81"><vector name="origin" x="69" y="74"/><string name="z" value="tamingMobRear"/><vector name="lt" x="-55" y="-72"/><vector name="rb" x="48" y="-11"/><imgdir name="map"><vector name="navel" x="0" y="-48"/></imgdir></canvas></imgdir></imgdir><imgdir name="jump"><imgdir name="0"><int name="delay" value="120"/><canvas name="cape" width="196" height="57"><vector name="origin" x="85" y="90"/><string name="z" value="tamingMobRear"/><vector name="lt" x="-55" y="-72"/><vector name="rb" x="48" y="-11"/><imgdir name="map"><vector name="navel" x="0" y="-46"/></imgdir></canvas></imgdir></imgdir><imgdir name="prone"><imgdir name="0"><canvas name="cape" width="111" height="52"><vector name="origin" x="22" y="51"/><string name="z" value="tamingMobRear"/><vector name="lt" x="-55" y="-50"/><vector name="rb" x="48" y="0"/><imgdir name="map"><vector name="navel" x="11" y="-3"/></imgdir></canvas></imgdir></imgdir><imgdir name="ladder"><imgdir name="0"><int name="delay" value="250"/><canvas name="cape" width="71" height="87"><vector name="origin" x="35" y="43"/><string name="z" value="tamingMobFront"/><vector name="lt" x="-56" y="-133"/><vector name="rb" x="56" y="-33"/><imgdir name="map"><vector name="navel" x="1" y="-8"/></imgdir></canvas></imgdir><imgdir name="1"><int name="delay" value="250"/><canvas name="cape" width="71" height="87"><vector name="origin" x="35" y="43"/><string name="z" value="tamingMobFront"/><vector name="lt" x="-56" y="-133"/><vector name="rb" x="56" y="-33"/><imgdir name="map"><vector name="navel" x="1" y="-8"/></imgdir></canvas></imgdir><imgdir name="2"><int name="delay" value="250"/><canvas name="cape" width="73" height="86"><vector name="origin" x="36" y="43"/><string name="z" value="tamingMobFront"/><vector name="lt" x="-56" y="-133"/><vector name="rb" x="56" y="-33"/><imgdir name="map"><vector name="navel" x="1" y="-8"/></imgdir></canvas></imgdir><imgdir name="3"><int name="delay" value="250"/><canvas name="cape" width="73" height="86"><vector name="origin" x="36" y="43"/><string name="z" value="tamingMobFront"/><vector name="lt" x="-56" y="-133"/><vector name="rb" x="56" y="-33"/><imgdir name="map"><vector name="navel" x="1" y="-8"/></imgdir></canvas></imgdir><imgdir name="4"><int name="delay" value="250"/><canvas name="cape" width="73" height="86"><vector name="origin" x="36" y="43"/><string name="z" value="tamingMobFront"/><vector name="lt" x="-56" y="-133"/><vector name="rb" x="56" y="-33"/><imgdir name="map"><vector name="navel" x="1" y="-8"/></imgdir></canvas></imgdir><imgdir name="5"><int name="delay" value="250"/><canvas name="cape" width="71" height="87"><vector name="origin" x="35" y="43"/><string name="z" value="tamingMobFront"/><vector name="lt" x="-56" y="-133"/><vector name="rb" x="56" y="-33"/><imgdir name="map"><vector name="navel" x="1" y="-8"/></imgdir></canvas></imgdir></imgdir><imgdir name="rope"><imgdir name="0"><int name="delay" value="250"/><canvas name="cape" width="71" height="87"><vector name="origin" x="35" y="43"/><string name="z" value="tamingMobFront"/><vector name="lt" x="-56" y="-133"/><vector name="rb" x="56" y="-33"/><imgdir name="map"><vector name="navel" x="1" y="-8"/></imgdir></canvas></imgdir><imgdir name="1"><int name="delay" value="250"/><canvas name="cape" width="71" height="87"><vector name="origin" x="35" y="43"/><string name="z" value="tamingMobFront"/><vector name="lt" x="-56" y="-133"/><vector name="rb" x="56" y="-33"/><imgdir name="map"><vector name="navel" x="1" y="-8"/></imgdir></canvas></imgdir><imgdir name="2"><int name="delay" value="250"/><canvas name="cape" width="73" height="86"><vector name="origin" x="36" y="43"/><string name="z" value="tamingMobFront"/><vector name="lt" x="-56" y="-133"/><vector name="rb" x="56" y="-33"/><imgdir name="map"><vector name="navel" x="1" y="-8"/></imgdir></canvas></imgdir><imgdir name="3"><int name="delay" value="250"/><canvas name="cape" width="73" height="86"><vector name="origin" x="36" y="43"/><string name="z" value="tamingMobFront"/><vector name="lt" x="-56" y="-133"/><vector name="rb" x="56" y="-33"/><imgdir name="map"><vector name="navel" x="1" y="-8"/></imgdir></canvas></imgdir><imgdir name="4"><int name="delay" value="250"/><canvas name="cape" width="73" height="86"><vector name="origin" x="36" y="43"/><string name="z" value="tamingMobFront"/><vector name="lt" x="-56" y="-133"/><vector name="rb" x="56" y="-33"/><imgdir name="map"><vector name="navel" x="1" y="-8"/></imgdir></canvas></imgdir><imgdir name="5"><int name="delay" value="250"/><canvas name="cape" width="71" height="87"><vector name="origin" x="35" y="43"/><string name="z" value="tamingMobFront"/><vector name="lt" x="-56" y="-133"/><vector name="rb" x="56" y="-33"/><imgdir name="map"><vector name="navel" x="1" y="-8"/></imgdir></canvas></imgdir></imgdir><imgdir name="fly"><imgdir name="0"><int name="delay" value="120"/><canvas name="cape" width="196" height="57"><vector name="origin" x="85" y="90"/><string name="z" value="tamingMobRear"/><vector name="lt" x="-55" y="-72"/><vector name="rb" x="48" y="-11"/><imgdir name="map"><vector name="navel" x="0" y="-46"/></imgdir></canvas></imgdir><imgdir name="1"><int name="delay" value="120"/><canvas name="cape" width="194" height="55"><vector name="origin" x="85" y="98"/><string name="z" value="tamingMobRear"/><vector name="lt" x="-55" y="-72"/><vector name="rb" x="48" y="-11"/><imgdir name="map"><vector name="navel" x="0" y="-45"/></imgdir></canvas></imgdir><imgdir name="2"><int name="delay" value="120"/><canvas name="cape" width="210" height="54"><vector name="origin" x="94" y="96"/><string name="z" value="tamingMobRear"/><vector name="lt" x="-55" y="-72"/><vector name="rb" x="48" y="-11"/><imgdir name="map"><vector name="navel" x="0" y="-44"/></imgdir></canvas></imgdir><imgdir name="3"><int name="delay" value="120"/><canvas name="cape" width="202" height="56"><vector name="origin" x="93" y="59"/><string name="z" value="tamingMobRear"/><vector name="lt" x="-55" y="-72"/><vector name="rb" x="48" y="-11"/><imgdir name="map"><vector name="navel" x="0" y="-46"/></imgdir></canvas></imgdir><imgdir name="4"><int name="delay" value="120"/><canvas name="cape" width="174" height="72"><vector name="origin" x="84" y="62"/><string name="z" value="tamingMobRear"/><vector name="lt" x="-55" y="-72"/><vector name="rb" x="48" y="-11"/><imgdir name="map"><vector name="navel" x="0" y="-47"/></imgdir></canvas></imgdir><imgdir name="5"><int name="delay" value="120"/><canvas name="cape" width="146" height="81"><vector name="origin" x="69" y="74"/><string name="z" value="tamingMobRear"/><vector name="lt" x="-55" y="-72"/><vector name="rb" x="48" y="-11"/><imgdir name="map"><vector name="navel" x="0" y="-48"/></imgdir></canvas></imgdir></imgdir><imgdir name="ride3"><imgdir name="0"><int name="delay" value="140"/><canvas name="0" width="1" height="1"><vector name="origin" x="0" y="0"/><string name="z" value="tamingMobRear"/><vector name="lt" x="-55" y="-72"/><vector name="rb" x="48" y="-11"/><imgdir name="map"><vector name="navel" x="-2" y="-32"/></imgdir></canvas></imgdir><imgdir name="1"><int name="delay" value="140"/><canvas name="0" width="171" height="69"><vector name="origin" x="84" y="29"/><string name="z" value="tamingMobRear"/><vector name="lt" x="-55" y="-72"/><vector name="rb" x="48" y="-11"/><imgdir name="map"><vector name="navel" x="-2" y="-16"/></imgdir></canvas></imgdir><imgdir name="2"><int name="delay" value="140"/><canvas name="0" width="207" height="54"><vector name="origin" x="93" y="96"/><string name="z" value="tamingMobRear"/><vector name="lt" x="-55" y="-72"/><vector name="rb" x="48" y="-11"/><imgdir name="map"><vector name="navel" x="-2" y="-43"/></imgdir></canvas></imgdir><imgdir name="3"><int name="delay" value="140"/><canvas name="0" width="202" height="56"><vector name="origin" x="93" y="59"/><string name="z" value="tamingMobRear"/><vector name="lt" x="-55" y="-72"/><vector name="rb" x="48" y="-11"/><imgdir name="map"><vector name="navel" x="-3" y="-45"/></imgdir></canvas></imgdir><imgdir name="4"><int name="delay" value="140"/><canvas name="0" width="174" height="69"><vector name="origin" x="86" y="62"/><string name="z" value="tamingMobRear"/><vector name="lt" x="-55" y="-72"/><vector name="rb" x="48" y="-11"/><imgdir name="map"><vector name="navel" x="-2" y="-44"/></imgdir></canvas></imgdir><imgdir name="5"><int name="delay" value="140"/><canvas name="0" width="146" height="81"><vector name="origin" x="71" y="74"/><string name="z" value="tamingMobRear"/><vector name="lt" x="-55" y="-72"/><vector name="rb" x="48" y="-11"/><imgdir name="map"><vector name="navel" x="-2" y="-47"/></imgdir></canvas></imgdir><imgdir name="6"><int name="delay" value="140"/><canvas name="0" width="196" height="57"><vector name="origin" x="88" y="76"/><string name="z" value="tamingMobRear"/><vector name="lt" x="-55" y="-72"/><vector name="rb" x="48" y="-11"/><imgdir name="map"><vector name="navel" x="-2" y="-32"/></imgdir></canvas></imgdir><imgdir name="7"><int name="delay" value="140"/><canvas name="0" width="194" height="55"><vector name="origin" x="87" y="98"/><string name="z" value="tamingMobRear"/><vector name="lt" x="-55" y="-72"/><vector name="rb" x="48" y="-11"/><imgdir name="map"><vector name="navel" x="-2" y="-44"/></imgdir></canvas></imgdir><imgdir name="8"><int name="delay" value="140"/><canvas name="0" width="207" height="54"><vector name="origin" x="93" y="96"/><string name="z" value="tamingMobRear"/><vector name="lt" x="-55" y="-72"/><vector name="rb" x="48" y="-11"/><imgdir name="map"><vector name="navel" x="-2" y="-43"/></imgdir></canvas></imgdir><imgdir name="9"><int name="delay" value="140"/><canvas name="0" width="202" height="56"><vector name="origin" x="93" y="59"/><string name="z" value="tamingMobRear"/><vector name="lt" x="-55" y="-72"/><vector name="rb" x="48" y="-11"/><imgdir name="map"><vector name="navel" x="-3" y="-45"/></imgdir></canvas></imgdir><imgdir name="10"><int name="delay" value="140"/><canvas name="0" width="174" height="69"><vector name="origin" x="86" y="62"/><string name="z" value="tamingMobRear"/><vector name="lt" x="-55" y="-72"/><vector name="rb" x="48" y="-11"/><imgdir name="map"><vector name="navel" x="-2" y="-44"/></imgdir></canvas></imgdir><imgdir name="11"><int name="delay" value="140"/><canvas name="0" width="146" height="81"><vector name="origin" x="71" y="74"/><string name="z" value="tamingMobRear"/><vector name="lt" x="-55" y="-72"/><vector name="rb" x="48" y="-11"/><imgdir name="map"><vector name="navel" x="-2" y="-47"/></imgdir></canvas></imgdir><imgdir name="12"><int name="delay" value="140"/><canvas name="0" width="174" height="69"><vector name="origin" x="86" y="62"/><string name="z" value="tamingMobRear"/><vector name="lt" x="-55" y="-72"/><vector name="rb" x="48" y="-11"/><imgdir name="map"><vector name="navel" x="-2" y="-44"/></imgdir></canvas></imgdir><imgdir name="13"><int name="delay" value="140"/><canvas name="0" width="146" height="81"><vector name="origin" x="71" y="74"/><string name="z" value="tamingMobRear"/><vector name="lt" x="-55" y="-72"/><vector name="rb" x="48" y="-11"/><imgdir name="map"><vector name="navel" x="-2" y="-47"/></imgdir></canvas></imgdir><imgdir name="14"><int name="delay" value="140"/><canvas name="0" width="146" height="81"><vector name="origin" x="71" y="74"/><string name="z" value="tamingMobRear"/><vector name="lt" x="-55" y="-72"/><vector name="rb" x="48" y="-11"/><imgdir name="map"><vector name="navel" x="-2" y="-47"/></imgdir></canvas></imgdir></imgdir><imgdir name="getoff3"><imgdir name="0"><int name="delay" value="240"/><canvas name="0" width="196" height="57"><vector name="origin" x="87" y="92"/><string name="z" value="tamingMobRear"/><vector name="lt" x="-55" y="-72"/><vector name="rb" x="48" y="-11"/><imgdir name="map"><vector name="navel" x="-2" y="-46"/></imgdir></canvas></imgdir><imgdir name="1"><int name="delay" value="60"/><canvas name="0" width="194" height="55"><vector name="origin" x="87" y="99"/><string name="z" value="tamingMobRear"/><vector name="lt" x="-55" y="-72"/><vector name="rb" x="48" y="-11"/><imgdir name="map"><vector name="navel" x="-2" y="-43"/></imgdir></canvas></imgdir><imgdir name="2"><int name="delay" value="60"/><canvas name="0" width="201" height="56"><vector name="origin" x="92" y="59"/><string name="z" value="tamingMobRear"/><vector name="lt" x="-55" y="-72"/><vector name="rb" x="48" y="-11"/><imgdir name="map"><vector name="navel" x="-2" y="-42"/></imgdir></canvas></imgdir><imgdir name="3"><int name="delay" value="60"/><canvas name="0" width="174" height="71"><vector name="origin" x="86" y="54"/><string name="z" value="tamingMobRear"/><vector name="lt" x="-55" y="-72"/><vector name="rb" x="48" y="-11"/><imgdir name="map"><vector name="navel" x="-3" y="-38"/></imgdir></canvas></imgdir><imgdir name="4"><int name="delay" value="60"/><canvas name="0" width="146" height="81"><vector name="origin" x="71" y="59"/><string name="z" value="tamingMobRear"/><vector name="lt" x="-55" y="-72"/><vector name="rb" x="48" y="-11"/><imgdir name="map"><vector name="navel" x="-2" y="-32"/></imgdir></canvas></imgdir><imgdir name="5"><int name="delay" value="60"/><canvas name="0" width="196" height="57"><vector name="origin" x="87" y="69"/><string name="z" value="tamingMobRear"/><vector name="lt" x="-55" y="-72"/><vector name="rb" x="48" y="-11"/><imgdir name="map"><vector name="navel" x="-2" y="-23"/></imgdir></canvas></imgdir></imgdir><imgdir name="alert"><imgdir name="0"><int name="delay" value="120"/><canvas name="cape" width="196" height="57"><vector name="origin" x="85" y="90"/><string name="z" value="tamingMobRear"/><vector name="lt" x="-55" y="-72"/><vector name="rb" x="48" y="-11"/><imgdir name="map"><vector name="navel" x="0" y="-46"/></imgdir></canvas></imgdir><imgdir name="1"><int name="delay" value="120"/><canvas name="cape" width="194" height="55"><vector name="origin" x="85" y="98"/><string name="z" value="tamingMobRear"/><vector name="lt" x="-55" y="-72"/><vector name="rb" x="48" y="-11"/><imgdir name="map"><vector name="navel" x="0" y="-45"/></imgdir></canvas></imgdir><imgdir name="2"><int name="delay" value="120"/><canvas name="cape" width="210" height="54"><vector name="origin" x="94" y="96"/><string name="z" value="tamingMobRear"/><vector name="lt" x="-55" y="-72"/><vector name="rb" x="48" y="-11"/><imgdir name="map"><vector name="navel" x="0" y="-44"/></imgdir></canvas></imgdir><imgdir name="3"><int name="delay" value="120"/><canvas name="cape" width="202" height="56"><vector name="origin" x="93" y="59"/><string name="z" value="tamingMobRear"/><vector name="lt" x="-55" y="-72"/><vector name="rb" x="48" y="-11"/><imgdir name="map"><vector name="navel" x="0" y="-46"/></imgdir></canvas></imgdir><imgdir name="4"><int name="delay" value="120"/><canvas name="cape" width="174" height="72"><vector name="origin" x="84" y="62"/><string name="z" value="tamingMobRear"/><vector name="lt" x="-55" y="-72"/><vector name="rb" x="48" y="-11"/><imgdir name="map"><vector name="navel" x="0" y="-47"/></imgdir></canvas></imgdir><imgdir name="5"><int name="delay" value="120"/><canvas name="cape" width="146" height="81"><vector name="origin" x="69" y="74"/><string name="z" value="tamingMobRear"/><vector name="lt" x="-55" y="-72"/><vector name="rb" x="48" y="-11"/><imgdir name="map"><vector name="navel" x="0" y="-48"/></imgdir></canvas></imgdir></imgdir><imgdir name="heal"><imgdir name="0"><int name="delay" value="120"/><canvas name="cape" width="196" height="57"><vector name="origin" x="85" y="90"/><string name="z" value="tamingMobRear"/><vector name="lt" x="-55" y="-72"/><vector name="rb" x="48" y="-11"/><imgdir name="map"><vector name="navel" x="0" y="-46"/></imgdir></canvas></imgdir><imgdir name="1"><int name="delay" value="120"/><canvas name="cape" width="194" height="55"><vector name="origin" x="85" y="98"/><string name="z" value="tamingMobRear"/><vector name="lt" x="-55" y="-72"/><vector name="rb" x="48" y="-11"/><imgdir name="map"><vector name="navel" x="0" y="-45"/></imgdir></canvas></imgdir><imgdir name="2"><int name="delay" value="120"/><canvas name="cape" width="210" height="54"><vector name="origin" x="94" y="96"/><string name="z" value="tamingMobRear"/><vector name="lt" x="-55" y="-72"/><vector name="rb" x="48" y="-11"/><imgdir name="map"><vector name="navel" x="0" y="-44"/></imgdir></canvas></imgdir><imgdir name="3"><int name="delay" value="120"/><canvas name="cape" width="202" height="56"><vector name="origin" x="93" y="59"/><string name="z" value="tamingMobRear"/><vector name="lt" x="-55" y="-72"/><vector name="rb" x="48" y="-11"/><imgdir name="map"><vector name="navel" x="0" y="-46"/></imgdir></canvas></imgdir><imgdir name="4"><int name="delay" value="120"/><canvas name="cape" width="174" height="72"><vector name="origin" x="84" y="62"/><string name="z" value="tamingMobRear"/><vector name="lt" x="-55" y="-72"/><vector name="rb" x="48" y="-11"/><imgdir name="map"><vector name="navel" x="0" y="-47"/></imgdir></canvas></imgdir><imgdir name="5"><int name="delay" value="120"/><canvas name="cape" width="146" height="81"><vector name="origin" x="69" y="74"/><string name="z" value="tamingMobRear"/><vector name="lt" x="-55" y="-72"/><vector name="rb" x="48" y="-11"/><imgdir name="map"><vector name="navel" x="0" y="-48"/></imgdir></canvas></imgdir></imgdir><imgdir name="proneStab"><imgdir name="0"><canvas name="cape" width="111" height="52"><vector name="origin" x="22" y="51"/><string name="z" value="tamingMobRear"/><vector name="lt" x="-55" y="-50"/><vector name="rb" x="48" y="0"/><imgdir name="map"><vector name="navel" x="11" y="-3"/></imgdir></canvas></imgdir></imgdir><imgdir name="shoot1"><imgdir name="0"><int name="delay" value="120"/><canvas name="cape" width="196" height="57"><vector name="origin" x="85" y="90"/><string name="z" value="tamingMobRear"/><vector name="lt" x="-55" y="-72"/><vector name="rb" x="48" y="-11"/><imgdir name="map"><vector name="navel" x="0" y="-46"/></imgdir></canvas></imgdir><imgdir name="1"><int name="delay" value="120"/><canvas name="cape" width="194" height="55"><vector name="origin" x="85" y="98"/><string name="z" value="tamingMobRear"/><vector name="lt" x="-55" y="-72"/><vector name="rb" x="48" y="-11"/><imgdir name="map"><vector name="navel" x="0" y="-45"/></imgdir></canvas></imgdir><imgdir name="2"><int name="delay" value="120"/><canvas name="cape" width="210" height="54"><vector name="origin" x="94" y="96"/><string name="z" value="tamingMobRear"/><vector name="lt" x="-55" y="-72"/><vector name="rb" x="48" y="-11"/><imgdir name="map"><vector name="navel" x="0" y="-44"/></imgdir></canvas></imgdir><imgdir name="3"><int name="delay" value="120"/><canvas name="cape" width="202" height="56"><vector name="origin" x="93" y="59"/><string name="z" value="tamingMobRear"/><vector name="lt" x="-55" y="-72"/><vector name="rb" x="48" y="-11"/><imgdir name="map"><vector name="navel" x="0" y="-46"/></imgdir></canvas></imgdir><imgdir name="4"><int name="delay" value="120"/><canvas name="cape" width="174" height="72"><vector name="origin" x="84" y="62"/><string name="z" value="tamingMobRear"/><vector name="lt" x="-55" y="-72"/><vector name="rb" x="48" y="-11"/><imgdir name="map"><vector name="navel" x="0" y="-47"/></imgdir></canvas></imgdir><imgdir name="5"><int name="delay" value="120"/><canvas name="cape" width="146" height="81"><vector name="origin" x="69" y="74"/><string name="z" value="tamingMobRear"/><vector name="lt" x="-55" y="-72"/><vector name="rb" x="48" y="-11"/><imgdir name="map"><vector name="navel" x="0" y="-48"/></imgdir></canvas></imgdir></imgdir><imgdir name="shoot2"><imgdir name="0"><int name="delay" value="120"/><canvas name="cape" width="196" height="57"><vector name="origin" x="85" y="90"/><string name="z" value="tamingMobRear"/><vector name="lt" x="-55" y="-72"/><vector name="rb" x="48" y="-11"/><imgdir name="map"><vector name="navel" x="0" y="-46"/></imgdir></canvas></imgdir><imgdir name="1"><int name="delay" value="120"/><canvas name="cape" width="194" height="55"><vector name="origin" x="85" y="98"/><string name="z" value="tamingMobRear"/><vector name="lt" x="-55" y="-72"/><vector name="rb" x="48" y="-11"/><imgdir name="map"><vector name="navel" x="0" y="-45"/></imgdir></canvas></imgdir><imgdir name="2"><int name="delay" value="120"/><canvas name="cape" width="210" height="54"><vector name="origin" x="94" y="96"/><string name="z" value="tamingMobRear"/><vector name="lt" x="-55" y="-72"/><vector name="rb" x="48" y="-11"/><imgdir name="map"><vector name="navel" x="0" y="-44"/></imgdir></canvas></imgdir><imgdir name="3"><int name="delay" value="120"/><canvas name="cape" width="202" height="56"><vector name="origin" x="93" y="59"/><string name="z" value="tamingMobRear"/><vector name="lt" x="-55" y="-72"/><vector name="rb" x="48" y="-11"/><imgdir name="map"><vector name="navel" x="0" y="-46"/></imgdir></canvas></imgdir><imgdir name="4"><int name="delay" value="120"/><canvas name="cape" width="174" height="72"><vector name="origin" x="84" y="62"/><string name="z" value="tamingMobRear"/><vector name="lt" x="-55" y="-72"/><vector name="rb" x="48" y="-11"/><imgdir name="map"><vector name="navel" x="0" y="-47"/></imgdir></canvas></imgdir><imgdir name="5"><int name="delay" value="120"/><canvas name="cape" width="146" height="81"><vector name="origin" x="69" y="74"/><string name="z" value="tamingMobRear"/><vector name="lt" x="-55" y="-72"/><vector name="rb" x="48" y="-11"/><imgdir name="map"><vector name="navel" x="0" y="-48"/></imgdir></canvas></imgdir></imgdir><imgdir name="shootF"><imgdir name="0"><int name="delay" value="120"/><canvas name="cape" width="196" height="57"><vector name="origin" x="85" y="90"/><string name="z" value="tamingMobRear"/><vector name="lt" x="-55" y="-72"/><vector name="rb" x="48" y="-11"/><imgdir name="map"><vector name="navel" x="0" y="-46"/></imgdir></canvas></imgdir><imgdir name="1"><int name="delay" value="120"/><canvas name="cape" width="194" height="55"><vector name="origin" x="85" y="98"/><string name="z" value="tamingMobRear"/><vector name="lt" x="-55" y="-72"/><vector name="rb" x="48" y="-11"/><imgdir name="map"><vector name="navel" x="0" y="-45"/></imgdir></canvas></imgdir><imgdir name="2"><int name="delay" value="120"/><canvas name="cape" width="210" height="54"><vector name="origin" x="94" y="96"/><string name="z" value="tamingMobRear"/><vector name="lt" x="-55" y="-72"/><vector name="rb" x="48" y="-11"/><imgdir name="map"><vector name="navel" x="0" y="-44"/></imgdir></canvas></imgdir><imgdir name="3"><int name="delay" value="120"/><canvas name="cape" width="202" height="56"><vector name="origin" x="93" y="59"/><string name="z" value="tamingMobRear"/><vector name="lt" x="-55" y="-72"/><vector name="rb" x="48" y="-11"/><imgdir name="map"><vector name="navel" x="0" y="-46"/></imgdir></canvas></imgdir><imgdir name="4"><int name="delay" value="120"/><canvas name="cape" width="174" height="72"><vector name="origin" x="84" y="62"/><string name="z" value="tamingMobRear"/><vector name="lt" x="-55" y="-72"/><vector name="rb" x="48" y="-11"/><imgdir name="map"><vector name="navel" x="0" y="-47"/></imgdir></canvas></imgdir><imgdir name="5"><int name="delay" value="120"/><canvas name="cape" width="146" height="81"><vector name="origin" x="69" y="74"/><string name="z" value="tamingMobRear"/><vector name="lt" x="-55" y="-72"/><vector name="rb" x="48" y="-11"/><imgdir name="map"><vector name="navel" x="0" y="-48"/></imgdir></canvas></imgdir></imgdir><imgdir name="sit"><imgdir name="0"><int name="delay" value="120"/><canvas name="cape" width="196" height="57"><vector name="origin" x="85" y="90"/><string name="z" value="tamingMobRear"/><vector name="lt" x="-55" y="-72"/><vector name="rb" x="48" y="-11"/><imgdir name="map"><vector name="navel" x="0" y="-46"/></imgdir></canvas></imgdir><imgdir name="1"><int name="delay" value="120"/><canvas name="cape" width="194" height="55"><vector name="origin" x="85" y="98"/><string name="z" value="tamingMobRear"/><vector name="lt" x="-55" y="-72"/><vector name="rb" x="48" y="-11"/><imgdir name="map"><vector name="navel" x="0" y="-45"/></imgdir></canvas></imgdir><imgdir name="2"><int name="delay" value="120"/><canvas name="cape" width="210" height="54"><vector name="origin" x="94" y="96"/><string name="z" value="tamingMobRear"/><vector name="lt" x="-55" y="-72"/><vector name="rb" x="48" y="-11"/><imgdir name="map"><vector name="navel" x="0" y="-44"/></imgdir></canvas></imgdir><imgdir name="3"><int name="delay" value="120"/><canvas name="cape" width="202" height="56"><vector name="origin" x="93" y="59"/><string name="z" value="tamingMobRear"/><vector name="lt" x="-55" y="-72"/><vector name="rb" x="48" y="-11"/><imgdir name="map"><vector name="navel" x="0" y="-46"/></imgdir></canvas></imgdir><imgdir name="4"><int name="delay" value="120"/><canvas name="cape" width="174" height="72"><vector name="origin" x="84" y="62"/><string name="z" value="tamingMobRear"/><vector name="lt" x="-55" y="-72"/><vector name="rb" x="48" y="-11"/><imgdir name="map"><vector name="navel" x="0" y="-47"/></imgdir></canvas></imgdir><imgdir name="5"><int name="delay" value="120"/><canvas name="cape" width="146" height="81"><vector name="origin" x="69" y="74"/><string name="z" value="tamingMobRear"/><vector name="lt" x="-55" y="-72"/><vector name="rb" x="48" y="-11"/><imgdir name="map"><vector name="navel" x="0" y="-48"/></imgdir></canvas></imgdir></imgdir><imgdir name="stabO1"><imgdir name="0"><int name="delay" value="120"/><canvas name="cape" width="196" height="57"><vector name="origin" x="85" y="90"/><string name="z" value="tamingMobRear"/><vector name="lt" x="-55" y="-72"/><vector name="rb" x="48" y="-11"/><imgdir name="map"><vector name="navel" x="0" y="-46"/></imgdir></canvas></imgdir><imgdir name="1"><int name="delay" value="120"/><canvas name="cape" width="194" height="55"><vector name="origin" x="85" y="98"/><string name="z" value="tamingMobRear"/><vector name="lt" x="-55" y="-72"/><vector name="rb" x="48" y="-11"/><imgdir name="map"><vector name="navel" x="0" y="-45"/></imgdir></canvas></imgdir><imgdir name="2"><int name="delay" value="120"/><canvas name="cape" width="210" height="54"><vector name="origin" x="94" y="96"/><string name="z" value="tamingMobRear"/><vector name="lt" x="-55" y="-72"/><vector name="rb" x="48" y="-11"/><imgdir name="map"><vector name="navel" x="0" y="-44"/></imgdir></canvas></imgdir><imgdir name="3"><int name="delay" value="120"/><canvas name="cape" width="202" height="56"><vector name="origin" x="93" y="59"/><string name="z" value="tamingMobRear"/><vector name="lt" x="-55" y="-72"/><vector name="rb" x="48" y="-11"/><imgdir name="map"><vector name="navel" x="0" y="-46"/></imgdir></canvas></imgdir><imgdir name="4"><int name="delay" value="120"/><canvas name="cape" width="174" height="72"><vector name="origin" x="84" y="62"/><string name="z" value="tamingMobRear"/><vector name="lt" x="-55" y="-72"/><vector name="rb" x="48" y="-11"/><imgdir name="map"><vector name="navel" x="0" y="-47"/></imgdir></canvas></imgdir><imgdir name="5"><int name="delay" value="120"/><canvas name="cape" width="146" height="81"><vector name="origin" x="69" y="74"/><string name="z" value="tamingMobRear"/><vector name="lt" x="-55" y="-72"/><vector name="rb" x="48" y="-11"/><imgdir name="map"><vector name="navel" x="0" y="-48"/></imgdir></canvas></imgdir></imgdir><imgdir name="stabO2"><imgdir name="0"><int name="delay" value="120"/><canvas name="cape" width="196" height="57"><vector name="origin" x="85" y="90"/><string name="z" value="tamingMobRear"/><vector name="lt" x="-55" y="-72"/><vector name="rb" x="48" y="-11"/><imgdir name="map"><vector name="navel" x="0" y="-46"/></imgdir></canvas></imgdir><imgdir name="1"><int name="delay" value="120"/><canvas name="cape" width="194" height="55"><vector name="origin" x="85" y="98"/><string name="z" value="tamingMobRear"/><vector name="lt" x="-55" y="-72"/><vector name="rb" x="48" y="-11"/><imgdir name="map"><vector name="navel" x="0" y="-45"/></imgdir></canvas></imgdir><imgdir name="2"><int name="delay" value="120"/><canvas name="cape" width="210" height="54"><vector name="origin" x="94" y="96"/><string name="z" value="tamingMobRear"/><vector name="lt" x="-55" y="-72"/><vector name="rb" x="48" y="-11"/><imgdir name="map"><vector name="navel" x="0" y="-44"/></imgdir></canvas></imgdir><imgdir name="3"><int name="delay" value="120"/><canvas name="cape" width="202" height="56"><vector name="origin" x="93" y="59"/><string name="z" value="tamingMobRear"/><vector name="lt" x="-55" y="-72"/><vector name="rb" x="48" y="-11"/><imgdir name="map"><vector name="navel" x="0" y="-46"/></imgdir></canvas></imgdir><imgdir name="4"><int name="delay" value="120"/><canvas name="cape" width="174" height="72"><vector name="origin" x="84" y="62"/><string name="z" value="tamingMobRear"/><vector name="lt" x="-55" y="-72"/><vector name="rb" x="48" y="-11"/><imgdir name="map"><vector name="navel" x="0" y="-47"/></imgdir></canvas></imgdir><imgdir name="5"><int name="delay" value="120"/><canvas name="cape" width="146" height="81"><vector name="origin" x="69" y="74"/><string name="z" value="tamingMobRear"/><vector name="lt" x="-55" y="-72"/><vector name="rb" x="48" y="-11"/><imgdir name="map"><vector name="navel" x="0" y="-48"/></imgdir></canvas></imgdir></imgdir><imgdir name="stabOF"><imgdir name="0"><int name="delay" value="120"/><canvas name="cape" width="196" height="57"><vector name="origin" x="85" y="90"/><string name="z" value="tamingMobRear"/><vector name="lt" x="-55" y="-72"/><vector name="rb" x="48" y="-11"/><imgdir name="map"><vector name="navel" x="0" y="-46"/></imgdir></canvas></imgdir><imgdir name="1"><int name="delay" value="120"/><canvas name="cape" width="194" height="55"><vector name="origin" x="85" y="98"/><string name="z" value="tamingMobRear"/><vector name="lt" x="-55" y="-72"/><vector name="rb" x="48" y="-11"/><imgdir name="map"><vector name="navel" x="0" y="-45"/></imgdir></canvas></imgdir><imgdir name="2"><int name="delay" value="120"/><canvas name="cape" width="210" height="54"><vector name="origin" x="94" y="96"/><string name="z" value="tamingMobRear"/><vector name="lt" x="-55" y="-72"/><vector name="rb" x="48" y="-11"/><imgdir name="map"><vector name="navel" x="0" y="-44"/></imgdir></canvas></imgdir><imgdir name="3"><int name="delay" value="120"/><canvas name="cape" width="202" height="56"><vector name="origin" x="93" y="59"/><string name="z" value="tamingMobRear"/><vector name="lt" x="-55" y="-72"/><vector name="rb" x="48" y="-11"/><imgdir name="map"><vector name="navel" x="0" y="-46"/></imgdir></canvas></imgdir><imgdir name="4"><int name="delay" value="120"/><canvas name="cape" width="174" height="72"><vector name="origin" x="84" y="62"/><string name="z" value="tamingMobRear"/><vector name="lt" x="-55" y="-72"/><vector name="rb" x="48" y="-11"/><imgdir name="map"><vector name="navel" x="0" y="-47"/></imgdir></canvas></imgdir><imgdir name="5"><int name="delay" value="120"/><canvas name="cape" width="146" height="81"><vector name="origin" x="69" y="74"/><string name="z" value="tamingMobRear"/><vector name="lt" x="-55" y="-72"/><vector name="rb" x="48" y="-11"/><imgdir name="map"><vector name="navel" x="0" y="-48"/></imgdir></canvas></imgdir></imgdir><imgdir name="stabT1"><imgdir name="0"><int name="delay" value="120"/><canvas name="cape" width="196" height="57"><vector name="origin" x="85" y="90"/><string name="z" value="tamingMobRear"/><vector name="lt" x="-55" y="-72"/><vector name="rb" x="48" y="-11"/><imgdir name="map"><vector name="navel" x="0" y="-46"/></imgdir></canvas></imgdir><imgdir name="1"><int name="delay" value="120"/><canvas name="cape" width="194" height="55"><vector name="origin" x="85" y="98"/><string name="z" value="tamingMobRear"/><vector name="lt" x="-55" y="-72"/><vector name="rb" x="48" y="-11"/><imgdir name="map"><vector name="navel" x="0" y="-45"/></imgdir></canvas></imgdir><imgdir name="2"><int name="delay" value="120"/><canvas name="cape" width="210" height="54"><vector name="origin" x="94" y="96"/><string name="z" value="tamingMobRear"/><vector name="lt" x="-55" y="-72"/><vector name="rb" x="48" y="-11"/><imgdir name="map"><vector name="navel" x="0" y="-44"/></imgdir></canvas></imgdir><imgdir name="3"><int name="delay" value="120"/><canvas name="cape" width="202" height="56"><vector name="origin" x="93" y="59"/><string name="z" value="tamingMobRear"/><vector name="lt" x="-55" y="-72"/><vector name="rb" x="48" y="-11"/><imgdir name="map"><vector name="navel" x="0" y="-46"/></imgdir></canvas></imgdir><imgdir name="4"><int name="delay" value="120"/><canvas name="cape" width="174" height="72"><vector name="origin" x="84" y="62"/><string name="z" value="tamingMobRear"/><vector name="lt" x="-55" y="-72"/><vector name="rb" x="48" y="-11"/><imgdir name="map"><vector name="navel" x="0" y="-47"/></imgdir></canvas></imgdir><imgdir name="5"><int name="delay" value="120"/><canvas name="cape" width="146" height="81"><vector name="origin" x="69" y="74"/><string name="z" value="tamingMobRear"/><vector name="lt" x="-55" y="-72"/><vector name="rb" x="48" y="-11"/><imgdir name="map"><vector name="navel" x="0" y="-48"/></imgdir></canvas></imgdir></imgdir><imgdir name="stabT2"><imgdir name="0"><int name="delay" value="120"/><canvas name="cape" width="196" height="57"><vector name="origin" x="85" y="90"/><string name="z" value="tamingMobRear"/><vector name="lt" x="-55" y="-72"/><vector name="rb" x="48" y="-11"/><imgdir name="map"><vector name="navel" x="0" y="-46"/></imgdir></canvas></imgdir><imgdir name="1"><int name="delay" value="120"/><canvas name="cape" width="194" height="55"><vector name="origin" x="85" y="98"/><string name="z" value="tamingMobRear"/><vector name="lt" x="-55" y="-72"/><vector name="rb" x="48" y="-11"/><imgdir name="map"><vector name="navel" x="0" y="-45"/></imgdir></canvas></imgdir><imgdir name="2"><int name="delay" value="120"/><canvas name="cape" width="210" height="54"><vector name="origin" x="94" y="96"/><string name="z" value="tamingMobRear"/><vector name="lt" x="-55" y="-72"/><vector name="rb" x="48" y="-11"/><imgdir name="map"><vector name="navel" x="0" y="-44"/></imgdir></canvas></imgdir><imgdir name="3"><int name="delay" value="120"/><canvas name="cape" width="202" height="56"><vector name="origin" x="93" y="59"/><string name="z" value="tamingMobRear"/><vector name="lt" x="-55" y="-72"/><vector name="rb" x="48" y="-11"/><imgdir name="map"><vector name="navel" x="0" y="-46"/></imgdir></canvas></imgdir><imgdir name="4"><int name="delay" value="120"/><canvas name="cape" width="174" height="72"><vector name="origin" x="84" y="62"/><string name="z" value="tamingMobRear"/><vector name="lt" x="-55" y="-72"/><vector name="rb" x="48" y="-11"/><imgdir name="map"><vector name="navel" x="0" y="-47"/></imgdir></canvas></imgdir><imgdir name="5"><int name="delay" value="120"/><canvas name="cape" width="146" height="81"><vector name="origin" x="69" y="74"/><string name="z" value="tamingMobRear"/><vector name="lt" x="-55" y="-72"/><vector name="rb" x="48" y="-11"/><imgdir name="map"><vector name="navel" x="0" y="-48"/></imgdir></canvas></imgdir></imgdir><imgdir name="stabTF"><imgdir name="0"><int name="delay" value="120"/><canvas name="cape" width="196" height="57"><vector name="origin" x="85" y="90"/><string name="z" value="tamingMobRear"/><vector name="lt" x="-55" y="-72"/><vector name="rb" x="48" y="-11"/><imgdir name="map"><vector name="navel" x="0" y="-46"/></imgdir></canvas></imgdir><imgdir name="1"><int name="delay" value="120"/><canvas name="cape" width="194" height="55"><vector name="origin" x="85" y="98"/><string name="z" value="tamingMobRear"/><vector name="lt" x="-55" y="-72"/><vector name="rb" x="48" y="-11"/><imgdir name="map"><vector name="navel" x="0" y="-45"/></imgdir></canvas></imgdir><imgdir name="2"><int name="delay" value="120"/><canvas name="cape" width="210" height="54"><vector name="origin" x="94" y="96"/><string name="z" value="tamingMobRear"/><vector name="lt" x="-55" y="-72"/><vector name="rb" x="48" y="-11"/><imgdir name="map"><vector name="navel" x="0" y="-44"/></imgdir></canvas></imgdir><imgdir name="3"><int name="delay" value="120"/><canvas name="cape" width="202" height="56"><vector name="origin" x="93" y="59"/><string name="z" value="tamingMobRear"/><vector name="lt" x="-55" y="-72"/><vector name="rb" x="48" y="-11"/><imgdir name="map"><vector name="navel" x="0" y="-46"/></imgdir></canvas></imgdir><imgdir name="4"><int name="delay" value="120"/><canvas name="cape" width="174" height="72"><vector name="origin" x="84" y="62"/><string name="z" value="tamingMobRear"/><vector name="lt" x="-55" y="-72"/><vector name="rb" x="48" y="-11"/><imgdir name="map"><vector name="navel" x="0" y="-47"/></imgdir></canvas></imgdir><imgdir name="5"><int name="delay" value="120"/><canvas name="cape" width="146" height="81"><vector name="origin" x="69" y="74"/><string name="z" value="tamingMobRear"/><vector name="lt" x="-55" y="-72"/><vector name="rb" x="48" y="-11"/><imgdir name="map"><vector name="navel" x="0" y="-48"/></imgdir></canvas></imgdir></imgdir><imgdir name="swingO1"><imgdir name="0"><int name="delay" value="120"/><canvas name="cape" width="196" height="57"><vector name="origin" x="85" y="90"/><string name="z" value="tamingMobRear"/><vector name="lt" x="-55" y="-72"/><vector name="rb" x="48" y="-11"/><imgdir name="map"><vector name="navel" x="0" y="-46"/></imgdir></canvas></imgdir><imgdir name="1"><int name="delay" value="120"/><canvas name="cape" width="194" height="55"><vector name="origin" x="85" y="98"/><string name="z" value="tamingMobRear"/><vector name="lt" x="-55" y="-72"/><vector name="rb" x="48" y="-11"/><imgdir name="map"><vector name="navel" x="0" y="-45"/></imgdir></canvas></imgdir><imgdir name="2"><int name="delay" value="120"/><canvas name="cape" width="210" height="54"><vector name="origin" x="94" y="96"/><string name="z" value="tamingMobRear"/><vector name="lt" x="-55" y="-72"/><vector name="rb" x="48" y="-11"/><imgdir name="map"><vector name="navel" x="0" y="-44"/></imgdir></canvas></imgdir><imgdir name="3"><int name="delay" value="120"/><canvas name="cape" width="202" height="56"><vector name="origin" x="93" y="59"/><string name="z" value="tamingMobRear"/><vector name="lt" x="-55" y="-72"/><vector name="rb" x="48" y="-11"/><imgdir name="map"><vector name="navel" x="0" y="-46"/></imgdir></canvas></imgdir><imgdir name="4"><int name="delay" value="120"/><canvas name="cape" width="174" height="72"><vector name="origin" x="84" y="62"/><string name="z" value="tamingMobRear"/><vector name="lt" x="-55" y="-72"/><vector name="rb" x="48" y="-11"/><imgdir name="map"><vector name="navel" x="0" y="-47"/></imgdir></canvas></imgdir><imgdir name="5"><int name="delay" value="120"/><canvas name="cape" width="146" height="81"><vector name="origin" x="69" y="74"/><string name="z" value="tamingMobRear"/><vector name="lt" x="-55" y="-72"/><vector name="rb" x="48" y="-11"/><imgdir name="map"><vector name="navel" x="0" y="-48"/></imgdir></canvas></imgdir></imgdir><imgdir name="swingO2"><imgdir name="0"><int name="delay" value="120"/><canvas name="cape" width="196" height="57"><vector name="origin" x="85" y="90"/><string name="z" value="tamingMobRear"/><vector name="lt" x="-55" y="-72"/><vector name="rb" x="48" y="-11"/><imgdir name="map"><vector name="navel" x="0" y="-46"/></imgdir></canvas></imgdir><imgdir name="1"><int name="delay" value="120"/><canvas name="cape" width="194" height="55"><vector name="origin" x="85" y="98"/><string name="z" value="tamingMobRear"/><vector name="lt" x="-55" y="-72"/><vector name="rb" x="48" y="-11"/><imgdir name="map"><vector name="navel" x="0" y="-45"/></imgdir></canvas></imgdir><imgdir name="2"><int name="delay" value="120"/><canvas name="cape" width="210" height="54"><vector name="origin" x="94" y="96"/><string name="z" value="tamingMobRear"/><vector name="lt" x="-55" y="-72"/><vector name="rb" x="48" y="-11"/><imgdir name="map"><vector name="navel" x="0" y="-44"/></imgdir></canvas></imgdir><imgdir name="3"><int name="delay" value="120"/><canvas name="cape" width="202" height="56"><vector name="origin" x="93" y="59"/><string name="z" value="tamingMobRear"/><vector name="lt" x="-55" y="-72"/><vector name="rb" x="48" y="-11"/><imgdir name="map"><vector name="navel" x="0" y="-46"/></imgdir></canvas></imgdir><imgdir name="4"><int name="delay" value="120"/><canvas name="cape" width="174" height="72"><vector name="origin" x="84" y="62"/><string name="z" value="tamingMobRear"/><vector name="lt" x="-55" y="-72"/><vector name="rb" x="48" y="-11"/><imgdir name="map"><vector name="navel" x="0" y="-47"/></imgdir></canvas></imgdir><imgdir name="5"><int name="delay" value="120"/><canvas name="cape" width="146" height="81"><vector name="origin" x="69" y="74"/><string name="z" value="tamingMobRear"/><vector name="lt" x="-55" y="-72"/><vector name="rb" x="48" y="-11"/><imgdir name="map"><vector name="navel" x="0" y="-48"/></imgdir></canvas></imgdir></imgdir><imgdir name="swingO3"><imgdir name="0"><int name="delay" value="120"/><canvas name="cape" width="196" height="57"><vector name="origin" x="85" y="90"/><string name="z" value="tamingMobRear"/><vector name="lt" x="-55" y="-72"/><vector name="rb" x="48" y="-11"/><imgdir name="map"><vector name="navel" x="0" y="-46"/></imgdir></canvas></imgdir><imgdir name="1"><int name="delay" value="120"/><canvas name="cape" width="194" height="55"><vector name="origin" x="85" y="98"/><string name="z" value="tamingMobRear"/><vector name="lt" x="-55" y="-72"/><vector name="rb" x="48" y="-11"/><imgdir name="map"><vector name="navel" x="0" y="-45"/></imgdir></canvas></imgdir><imgdir name="2"><int name="delay" value="120"/><canvas name="cape" width="210" height="54"><vector name="origin" x="94" y="96"/><string name="z" value="tamingMobRear"/><vector name="lt" x="-55" y="-72"/><vector name="rb" x="48" y="-11"/><imgdir name="map"><vector name="navel" x="0" y="-44"/></imgdir></canvas></imgdir><imgdir name="3"><int name="delay" value="120"/><canvas name="cape" width="202" height="56"><vector name="origin" x="93" y="59"/><string name="z" value="tamingMobRear"/><vector name="lt" x="-55" y="-72"/><vector name="rb" x="48" y="-11"/><imgdir name="map"><vector name="navel" x="0" y="-46"/></imgdir></canvas></imgdir><imgdir name="4"><int name="delay" value="120"/><canvas name="cape" width="174" height="72"><vector name="origin" x="84" y="62"/><string name="z" value="tamingMobRear"/><vector name="lt" x="-55" y="-72"/><vector name="rb" x="48" y="-11"/><imgdir name="map"><vector name="navel" x="0" y="-47"/></imgdir></canvas></imgdir><imgdir name="5"><int name="delay" value="120"/><canvas name="cape" width="146" height="81"><vector name="origin" x="69" y="74"/><string name="z" value="tamingMobRear"/><vector name="lt" x="-55" y="-72"/><vector name="rb" x="48" y="-11"/><imgdir name="map"><vector name="navel" x="0" y="-48"/></imgdir></canvas></imgdir></imgdir><imgdir name="swingOF"><imgdir name="0"><int name="delay" value="120"/><canvas name="cape" width="196" height="57"><vector name="origin" x="85" y="90"/><string name="z" value="tamingMobRear"/><vector name="lt" x="-55" y="-72"/><vector name="rb" x="48" y="-11"/><imgdir name="map"><vector name="navel" x="0" y="-46"/></imgdir></canvas></imgdir><imgdir name="1"><int name="delay" value="120"/><canvas name="cape" width="194" height="55"><vector name="origin" x="85" y="98"/><string name="z" value="tamingMobRear"/><vector name="lt" x="-55" y="-72"/><vector name="rb" x="48" y="-11"/><imgdir name="map"><vector name="navel" x="0" y="-45"/></imgdir></canvas></imgdir><imgdir name="2"><int name="delay" value="120"/><canvas name="cape" width="210" height="54"><vector name="origin" x="94" y="96"/><string name="z" value="tamingMobRear"/><vector name="lt" x="-55" y="-72"/><vector name="rb" x="48" y="-11"/><imgdir name="map"><vector name="navel" x="0" y="-44"/></imgdir></canvas></imgdir><imgdir name="3"><int name="delay" value="120"/><canvas name="cape" width="202" height="56"><vector name="origin" x="93" y="59"/><string name="z" value="tamingMobRear"/><vector name="lt" x="-55" y="-72"/><vector name="rb" x="48" y="-11"/><imgdir name="map"><vector name="navel" x="0" y="-46"/></imgdir></canvas></imgdir><imgdir name="4"><int name="delay" value="120"/><canvas name="cape" width="174" height="72"><vector name="origin" x="84" y="62"/><string name="z" value="tamingMobRear"/><vector name="lt" x="-55" y="-72"/><vector name="rb" x="48" y="-11"/><imgdir name="map"><vector name="navel" x="0" y="-47"/></imgdir></canvas></imgdir><imgdir name="5"><int name="delay" value="120"/><canvas name="cape" width="146" height="81"><vector name="origin" x="69" y="74"/><string name="z" value="tamingMobRear"/><vector name="lt" x="-55" y="-72"/><vector name="rb" x="48" y="-11"/><imgdir name="map"><vector name="navel" x="0" y="-48"/></imgdir></canvas></imgdir></imgdir><imgdir name="swingP1"><imgdir name="0"><int name="delay" value="120"/><canvas name="cape" width="196" height="57"><vector name="origin" x="85" y="90"/><string name="z" value="tamingMobRear"/><vector name="lt" x="-55" y="-72"/><vector name="rb" x="48" y="-11"/><imgdir name="map"><vector name="navel" x="0" y="-46"/></imgdir></canvas></imgdir><imgdir name="1"><int name="delay" value="120"/><canvas name="cape" width="194" height="55"><vector name="origin" x="85" y="98"/><string name="z" value="tamingMobRear"/><vector name="lt" x="-55" y="-72"/><vector name="rb" x="48" y="-11"/><imgdir name="map"><vector name="navel" x="0" y="-45"/></imgdir></canvas></imgdir><imgdir name="2"><int name="delay" value="120"/><canvas name="cape" width="210" height="54"><vector name="origin" x="94" y="96"/><string name="z" value="tamingMobRear"/><vector name="lt" x="-55" y="-72"/><vector name="rb" x="48" y="-11"/><imgdir name="map"><vector name="navel" x="0" y="-44"/></imgdir></canvas></imgdir><imgdir name="3"><int name="delay" value="120"/><canvas name="cape" width="202" height="56"><vector name="origin" x="93" y="59"/><string name="z" value="tamingMobRear"/><vector name="lt" x="-55" y="-72"/><vector name="rb" x="48" y="-11"/><imgdir name="map"><vector name="navel" x="0" y="-46"/></imgdir></canvas></imgdir><imgdir name="4"><int name="delay" value="120"/><canvas name="cape" width="174" height="72"><vector name="origin" x="84" y="62"/><string name="z" value="tamingMobRear"/><vector name="lt" x="-55" y="-72"/><vector name="rb" x="48" y="-11"/><imgdir name="map"><vector name="navel" x="0" y="-47"/></imgdir></canvas></imgdir><imgdir name="5"><int name="delay" value="120"/><canvas name="cape" width="146" height="81"><vector name="origin" x="69" y="74"/><string name="z" value="tamingMobRear"/><vector name="lt" x="-55" y="-72"/><vector name="rb" x="48" y="-11"/><imgdir name="map"><vector name="navel" x="0" y="-48"/></imgdir></canvas></imgdir></imgdir><imgdir name="swingP2"><imgdir name="0"><int name="delay" value="120"/><canvas name="cape" width="196" height="57"><vector name="origin" x="85" y="90"/><string name="z" value="tamingMobRear"/><vector name="lt" x="-55" y="-72"/><vector name="rb" x="48" y="-11"/><imgdir name="map"><vector name="navel" x="0" y="-46"/></imgdir></canvas></imgdir><imgdir name="1"><int name="delay" value="120"/><canvas name="cape" width="194" height="55"><vector name="origin" x="85" y="98"/><string name="z" value="tamingMobRear"/><vector name="lt" x="-55" y="-72"/><vector name="rb" x="48" y="-11"/><imgdir name="map"><vector name="navel" x="0" y="-45"/></imgdir></canvas></imgdir><imgdir name="2"><int name="delay" value="120"/><canvas name="cape" width="210" height="54"><vector name="origin" x="94" y="96"/><string name="z" value="tamingMobRear"/><vector name="lt" x="-55" y="-72"/><vector name="rb" x="48" y="-11"/><imgdir name="map"><vector name="navel" x="0" y="-44"/></imgdir></canvas></imgdir><imgdir name="3"><int name="delay" value="120"/><canvas name="cape" width="202" height="56"><vector name="origin" x="93" y="59"/><string name="z" value="tamingMobRear"/><vector name="lt" x="-55" y="-72"/><vector name="rb" x="48" y="-11"/><imgdir name="map"><vector name="navel" x="0" y="-46"/></imgdir></canvas></imgdir><imgdir name="4"><int name="delay" value="120"/><canvas name="cape" width="174" height="72"><vector name="origin" x="84" y="62"/><string name="z" value="tamingMobRear"/><vector name="lt" x="-55" y="-72"/><vector name="rb" x="48" y="-11"/><imgdir name="map"><vector name="navel" x="0" y="-47"/></imgdir></canvas></imgdir><imgdir name="5"><int name="delay" value="120"/><canvas name="cape" width="146" height="81"><vector name="origin" x="69" y="74"/><string name="z" value="tamingMobRear"/><vector name="lt" x="-55" y="-72"/><vector name="rb" x="48" y="-11"/><imgdir name="map"><vector name="navel" x="0" y="-48"/></imgdir></canvas></imgdir></imgdir><imgdir name="swingPF"><imgdir name="0"><int name="delay" value="120"/><canvas name="cape" width="196" height="57"><vector name="origin" x="85" y="90"/><string name="z" value="tamingMobRear"/><vector name="lt" x="-55" y="-72"/><vector name="rb" x="48" y="-11"/><imgdir name="map"><vector name="navel" x="0" y="-46"/></imgdir></canvas></imgdir><imgdir name="1"><int name="delay" value="120"/><canvas name="cape" width="194" height="55"><vector name="origin" x="85" y="98"/><string name="z" value="tamingMobRear"/><vector name="lt" x="-55" y="-72"/><vector name="rb" x="48" y="-11"/><imgdir name="map"><vector name="navel" x="0" y="-45"/></imgdir></canvas></imgdir><imgdir name="2"><int name="delay" value="120"/><canvas name="cape" width="210" height="54"><vector name="origin" x="94" y="96"/><string name="z" value="tamingMobRear"/><vector name="lt" x="-55" y="-72"/><vector name="rb" x="48" y="-11"/><imgdir name="map"><vector name="navel" x="0" y="-44"/></imgdir></canvas></imgdir><imgdir name="3"><int name="delay" value="120"/><canvas name="cape" width="202" height="56"><vector name="origin" x="93" y="59"/><string name="z" value="tamingMobRear"/><vector name="lt" x="-55" y="-72"/><vector name="rb" x="48" y="-11"/><imgdir name="map"><vector name="navel" x="0" y="-46"/></imgdir></canvas></imgdir><imgdir name="4"><int name="delay" value="120"/><canvas name="cape" width="174" height="72"><vector name="origin" x="84" y="62"/><string name="z" value="tamingMobRear"/><vector name="lt" x="-55" y="-72"/><vector name="rb" x="48" y="-11"/><imgdir name="map"><vector name="navel" x="0" y="-47"/></imgdir></canvas></imgdir><imgdir name="5"><int name="delay" value="120"/><canvas name="cape" width="146" height="81"><vector name="origin" x="69" y="74"/><string name="z" value="tamingMobRear"/><vector name="lt" x="-55" y="-72"/><vector name="rb" x="48" y="-11"/><imgdir name="map"><vector name="navel" x="0" y="-48"/></imgdir></canvas></imgdir></imgdir><imgdir name="swingT1"><imgdir name="0"><int name="delay" value="120"/><canvas name="cape" width="196" height="57"><vector name="origin" x="85" y="90"/><string name="z" value="tamingMobRear"/><vector name="lt" x="-55" y="-72"/><vector name="rb" x="48" y="-11"/><imgdir name="map"><vector name="navel" x="0" y="-46"/></imgdir></canvas></imgdir><imgdir name="1"><int name="delay" value="120"/><canvas name="cape" width="194" height="55"><vector name="origin" x="85" y="98"/><string name="z" value="tamingMobRear"/><vector name="lt" x="-55" y="-72"/><vector name="rb" x="48" y="-11"/><imgdir name="map"><vector name="navel" x="0" y="-45"/></imgdir></canvas></imgdir><imgdir name="2"><int name="delay" value="120"/><canvas name="cape" width="210" height="54"><vector name="origin" x="94" y="96"/><string name="z" value="tamingMobRear"/><vector name="lt" x="-55" y="-72"/><vector name="rb" x="48" y="-11"/><imgdir name="map"><vector name="navel" x="0" y="-44"/></imgdir></canvas></imgdir><imgdir name="3"><int name="delay" value="120"/><canvas name="cape" width="202" height="56"><vector name="origin" x="93" y="59"/><string name="z" value="tamingMobRear"/><vector name="lt" x="-55" y="-72"/><vector name="rb" x="48" y="-11"/><imgdir name="map"><vector name="navel" x="0" y="-46"/></imgdir></canvas></imgdir><imgdir name="4"><int name="delay" value="120"/><canvas name="cape" width="174" height="72"><vector name="origin" x="84" y="62"/><string name="z" value="tamingMobRear"/><vector name="lt" x="-55" y="-72"/><vector name="rb" x="48" y="-11"/><imgdir name="map"><vector name="navel" x="0" y="-47"/></imgdir></canvas></imgdir><imgdir name="5"><int name="delay" value="120"/><canvas name="cape" width="146" height="81"><vector name="origin" x="69" y="74"/><string name="z" value="tamingMobRear"/><vector name="lt" x="-55" y="-72"/><vector name="rb" x="48" y="-11"/><imgdir name="map"><vector name="navel" x="0" y="-48"/></imgdir></canvas></imgdir></imgdir><imgdir name="swingT2"><imgdir name="0"><int name="delay" value="120"/><canvas name="cape" width="196" height="57"><vector name="origin" x="85" y="90"/><string name="z" value="tamingMobRear"/><vector name="lt" x="-55" y="-72"/><vector name="rb" x="48" y="-11"/><imgdir name="map"><vector name="navel" x="0" y="-46"/></imgdir></canvas></imgdir><imgdir name="1"><int name="delay" value="120"/><canvas name="cape" width="194" height="55"><vector name="origin" x="85" y="98"/><string name="z" value="tamingMobRear"/><vector name="lt" x="-55" y="-72"/><vector name="rb" x="48" y="-11"/><imgdir name="map"><vector name="navel" x="0" y="-45"/></imgdir></canvas></imgdir><imgdir name="2"><int name="delay" value="120"/><canvas name="cape" width="210" height="54"><vector name="origin" x="94" y="96"/><string name="z" value="tamingMobRear"/><vector name="lt" x="-55" y="-72"/><vector name="rb" x="48" y="-11"/><imgdir name="map"><vector name="navel" x="0" y="-44"/></imgdir></canvas></imgdir><imgdir name="3"><int name="delay" value="120"/><canvas name="cape" width="202" height="56"><vector name="origin" x="93" y="59"/><string name="z" value="tamingMobRear"/><vector name="lt" x="-55" y="-72"/><vector name="rb" x="48" y="-11"/><imgdir name="map"><vector name="navel" x="0" y="-46"/></imgdir></canvas></imgdir><imgdir name="4"><int name="delay" value="120"/><canvas name="cape" width="174" height="72"><vector name="origin" x="84" y="62"/><string name="z" value="tamingMobRear"/><vector name="lt" x="-55" y="-72"/><vector name="rb" x="48" y="-11"/><imgdir name="map"><vector name="navel" x="0" y="-47"/></imgdir></canvas></imgdir><imgdir name="5"><int name="delay" value="120"/><canvas name="cape" width="146" height="81"><vector name="origin" x="69" y="74"/><string name="z" value="tamingMobRear"/><vector name="lt" x="-55" y="-72"/><vector name="rb" x="48" y="-11"/><imgdir name="map"><vector name="navel" x="0" y="-48"/></imgdir></canvas></imgdir></imgdir><imgdir name="swingT3"><imgdir name="0"><int name="delay" value="120"/><canvas name="cape" width="196" height="57"><vector name="origin" x="85" y="90"/><string name="z" value="tamingMobRear"/><vector name="lt" x="-55" y="-72"/><vector name="rb" x="48" y="-11"/><imgdir name="map"><vector name="navel" x="0" y="-46"/></imgdir></canvas></imgdir><imgdir name="1"><int name="delay" value="120"/><canvas name="cape" width="194" height="55"><vector name="origin" x="85" y="98"/><string name="z" value="tamingMobRear"/><vector name="lt" x="-55" y="-72"/><vector name="rb" x="48" y="-11"/><imgdir name="map"><vector name="navel" x="0" y="-45"/></imgdir></canvas></imgdir><imgdir name="2"><int name="delay" value="120"/><canvas name="cape" width="210" height="54"><vector name="origin" x="94" y="96"/><string name="z" value="tamingMobRear"/><vector name="lt" x="-55" y="-72"/><vector name="rb" x="48" y="-11"/><imgdir name="map"><vector name="navel" x="0" y="-44"/></imgdir></canvas></imgdir><imgdir name="3"><int name="delay" value="120"/><canvas name="cape" width="202" height="56"><vector name="origin" x="93" y="59"/><string name="z" value="tamingMobRear"/><vector name="lt" x="-55" y="-72"/><vector name="rb" x="48" y="-11"/><imgdir name="map"><vector name="navel" x="0" y="-46"/></imgdir></canvas></imgdir><imgdir name="4"><int name="delay" value="120"/><canvas name="cape" width="174" height="72"><vector name="origin" x="84" y="62"/><string name="z" value="tamingMobRear"/><vector name="lt" x="-55" y="-72"/><vector name="rb" x="48" y="-11"/><imgdir name="map"><vector name="navel" x="0" y="-47"/></imgdir></canvas></imgdir><imgdir name="5"><int name="delay" value="120"/><canvas name="cape" width="146" height="81"><vector name="origin" x="69" y="74"/><string name="z" value="tamingMobRear"/><vector name="lt" x="-55" y="-72"/><vector name="rb" x="48" y="-11"/><imgdir name="map"><vector name="navel" x="0" y="-48"/></imgdir></canvas></imgdir></imgdir><imgdir name="swingTF"><imgdir name="0"><int name="delay" value="120"/><canvas name="cape" width="196" height="57"><vector name="origin" x="85" y="90"/><string name="z" value="tamingMobRear"/><vector name="lt" x="-55" y="-72"/><vector name="rb" x="48" y="-11"/><imgdir name="map"><vector name="navel" x="0" y="-46"/></imgdir></canvas></imgdir><imgdir name="1"><int name="delay" value="120"/><canvas name="cape" width="194" height="55"><vector name="origin" x="85" y="98"/><string name="z" value="tamingMobRear"/><vector name="lt" x="-55" y="-72"/><vector name="rb" x="48" y="-11"/><imgdir name="map"><vector name="navel" x="0" y="-45"/></imgdir></canvas></imgdir><imgdir name="2"><int name="delay" value="120"/><canvas name="cape" width="210" height="54"><vector name="origin" x="94" y="96"/><string name="z" value="tamingMobRear"/><vector name="lt" x="-55" y="-72"/><vector name="rb" x="48" y="-11"/><imgdir name="map"><vector name="navel" x="0" y="-44"/></imgdir></canvas></imgdir><imgdir name="3"><int name="delay" value="120"/><canvas name="cape" width="202" height="56"><vector name="origin" x="93" y="59"/><string name="z" value="tamingMobRear"/><vector name="lt" x="-55" y="-72"/><vector name="rb" x="48" y="-11"/><imgdir name="map"><vector name="navel" x="0" y="-46"/></imgdir></canvas></imgdir><imgdir name="4"><int name="delay" value="120"/><canvas name="cape" width="174" height="72"><vector name="origin" x="84" y="62"/><string name="z" value="tamingMobRear"/><vector name="lt" x="-55" y="-72"/><vector name="rb" x="48" y="-11"/><imgdir name="map"><vector name="navel" x="0" y="-47"/></imgdir></canvas></imgdir><imgdir name="5"><int name="delay" value="120"/><canvas name="cape" width="146" height="81"><vector name="origin" x="69" y="74"/><string name="z" value="tamingMobRear"/><vector name="lt" x="-55" y="-72"/><vector name="rb" x="48" y="-11"/><imgdir name="map"><vector name="navel" x="0" y="-48"/></imgdir></canvas></imgdir></imgdir></imgdir>